{"total":162,"data":[{"id":"010102002-T","description":"BARRA ABATIBLE WC 78 CM","idCategory":1,"nameCategory":"BAÑO","stock":6.00000000,"externalCode":null,"internalCode":null,"active":true,"availableSale":true,"salePrice":47990.00000000},{"id":"010102003-T","description":"BARRA DUCHA DESLIZABLE 65 CM","idCategory":1,"nameCategory":"BAÑO","stock":5.00000000,"externalCode":null,"internalCode":null,"active":true,"availableSale":true,"salePrice":12920.00000000},{"id":"010102004-T","description":"BARRA SEGURIDAD RECTA 30 CM","idCategory":1,"nameCategory":"BAÑO","stock":3.00000000,"externalCode":null,"internalCode":null,"active":true,"availableSale":true,"salePrice":15990.00000000},{"id":"010102005-T","description":"BARRA SEGURIDAD RECTA 40 CM","idCategory":1,"nameCategory":"BAÑO","stock":2.00000000,"externalCode":null,"internalCode":null,"active":true,"availableSale":true,"salePrice":9285.00000000},{"id":"010102006-T","description":"Barra seguridad 60 cm acero inox.","idCategory":1,"nameCategory":"BAÑO","stock":4.00000000,"externalCode":null,"internalCode":null,"active":true,"availableSale":true,"salePrice":69990.00000000}],"type":0}